crazybee/YX.py
crazybee/__init__.py
crazybee/eMall.py
crazybee-0.0.1.dist-info/LICENSE
crazybee-0.0.1.dist-info/METADATA
crazybee-0.0.1.dist-info/WHEEL
crazybee-0.0.1.dist-info/top_level.txt
crazybee-0.0.1.dist-info/RECORD
