Metadata-Version: 2.1
Name: crazybee
Version: 0.0.1
Summary: crazybee to extract info from yanxuan website
Home-page: https://github.com
Author: handaochang
Author-email: hanleilei@outlook.com
License: UNKNOWN
Platform: UNKNOWN
Classifier: Programming Language :: Python :: 3.7
Classifier: License :: OSI Approved :: MIT License
Classifier: Operating System :: OS Independent
Requires-Dist: bs4
Requires-Dist: requests
Requires-Dist: xlwt
Requires-Dist: retrying
